{
    "adg": 0.05766171349140148,
    "adg_per_exposure_long": 0.006408637231608944,
    "adg_per_exposure_short": 0.0,
    "adg_w": 0.02997972251515719,
    "adg_w_per_exposure_long": 0.0033320058366387542,
    "adg_w_per_exposure_short": 0.0,
    "calmar_ratio": 0.12796432852729375,
    "calmar_ratio_w": 0.2900535863401647,
    "drawdown_worst": 0.4506077135324686,
    "drawdown_worst_mean_1pct": 0.45034584675139205,
    "equity_balance_diff_neg_max": 0.455825821674425,
    "equity_balance_diff_neg_mean": 0.01781439397880166,
    "equity_balance_diff_pos_max": 0.7481834650515313,
    "equity_balance_diff_pos_mean": 0.009807067588443932,
    "equity_choppiness": 1.242950450808944,
    "equity_choppiness_w": 1.198939692933384,
    "equity_jerkiness": 0.0943378484359532,
    "equity_jerkiness_w": 0.05130160381103523,
    "expected_shortfall_1pct": 0.4484562976287334,
    "exponential_fit_error": 0.8707849861373247,
    "exponential_fit_error_w": 0.09492891925338001,
    "gain": 227139.34832692367,
    "gain_per_exposure_long": 25244.71779126687,
    "gain_per_exposure_short": 0.0,
    "loss_profit_ratio": 0.01582527678465181,
    "loss_profit_ratio_long": 0.01582527678465181,
    "loss_profit_ratio_short": 1.0,
    "loss_profit_ratio_w": 0.005697320274662,
    "mdg": 0.024575910727328287,
    "mdg_per_exposure_long": 0.0027314154740014766,
    "mdg_per_exposure_short": 0.0,
    "mdg_w": 0.01352906155953489,
    "mdg_w_per_exposure_long": 0.0015036467418210492,
    "mdg_w_per_exposure_short": 0.0,
    "omega_ratio": 12.420312556064289,
    "omega_ratio_w": 13.947372006689472,
    "pnl_ratio_long_short": 1.0,
    "position_held_hours_max": 83.35,
    "position_held_hours_mean": 8.812383900928793,
    "position_held_hours_median": 4.1,
    "position_unchanged_hours_max": 63.53333333333333,
    "positions_held_per_day": 1.4681818181818183,
    "sharpe_ratio": 0.16329461864414704,
    "sharpe_ratio_w": 0.2889564671700012,
    "sortino_ratio": 0.41761208719900783,
    "sortino_ratio_w": 0.6707933766511774,
    "sterling_ratio": 0.12803873713358108,
    "sterling_ratio_w": 0.2900610272007935,
    "volume_pct_per_day_avg": 6.769498240101725,
    "volume_pct_per_day_avg_w": 3.9792599120669117
}