{
    "adg": 0.01436740570856343,
    "adg_per_exposure_long": 0.0016017174702969263,
    "adg_per_exposure_short": 0.0,
    "adg_w": 0.006567600880790492,
    "adg_w_per_exposure_long": 0.0007321740112363981,
    "adg_w_per_exposure_short": 0.0,
    "calmar_ratio": 0.04492961060098263,
    "calmar_ratio_w": 0.05114544622119952,
    "drawdown_worst": 0.31977587867741747,
    "drawdown_worst_mean_1pct": 0.2507913615908007,
    "equity_balance_diff_neg_max": 0.3316592721757342,
    "equity_balance_diff_neg_mean": 0.00592364864233315,
    "equity_balance_diff_pos_max": 0.33971882691754546,
    "equity_balance_diff_pos_mean": 0.010615517003454051,
    "equity_choppiness": 1.0916158734535388,
    "equity_choppiness_w": 1.0872884104840455,
    "equity_jerkiness": 0.024723758787324464,
    "equity_jerkiness_w": 0.012406593570736696,
    "expected_shortfall_1pct": 0.23626201779785574,
    "exponential_fit_error": 0.044636311342982134,
    "exponential_fit_error_w": 0.011134513290177244,
    "gain": 107.65983805569601,
    "gain_per_exposure_long": 12.002211600412041,
    "gain_per_exposure_short": 0.0,
    "loss_profit_ratio": 0.036630737463597435,
    "loss_profit_ratio_long": 0.036630737463597435,
    "loss_profit_ratio_short": 1.0,
    "loss_profit_ratio_w": 0.08128475577141563,
    "mdg": 3.3269710289969795e-05,
    "mdg_per_exposure_long": 3.7089978026722175e-06,
    "mdg_per_exposure_short": 0.0,
    "mdg_w": 3.3269710289969794e-06,
    "mdg_w_per_exposure_long": 3.7089978026722176e-07,
    "mdg_w_per_exposure_short": 0.0,
    "omega_ratio": 43.62429547022612,
    "omega_ratio_w": 61.381135977289475,
    "pnl_ratio_long_short": 1.0,
    "position_held_hours_max": 7.266666666666667,
    "position_held_hours_mean": 0.19560260586319217,
    "position_held_hours_median": 0.1,
    "position_unchanged_hours_max": 2.7666666666666666,
    "positions_held_per_day": 3.7439024390243905,
    "sharpe_ratio": 0.14777831112435308,
    "sharpe_ratio_w": 0.11134831911420369,
    "sortino_ratio": 0.2629954973601645,
    "sortino_ratio_w": 0.1718952112297462,
    "sterling_ratio": 0.05728827985712584,
    "sterling_ratio_w": 0.05238131314681384,
    "volume_pct_per_day_avg": 5.409655866040165,
    "volume_pct_per_day_avg_w": 3.611392109385819
}