{
    "adg": 0.020873171245570976,
    "adg_per_exposure_long": 0.004176304771022604,
    "adg_per_exposure_short": 0.0,
    "adg_w": 0.009593792502090092,
    "adg_w_per_exposure_long": 0.0019195263109423953,
    "adg_w_per_exposure_short": 0.0,
    "calmar_ratio": 0.07256545018192408,
    "calmar_ratio_w": 0.2572452311623702,
    "drawdown_worst": 0.28764613453428894,
    "drawdown_worst_mean_1pct": 0.2848684348857702,
    "equity_balance_diff_neg_max": 0.29139503220715857,
    "equity_balance_diff_neg_mean": 0.0054769957285000625,
    "equity_balance_diff_pos_max": 0.5598344654469324,
    "equity_balance_diff_pos_mean": 0.006065905015075374,
    "equity_choppiness": 1.181099743582414,
    "equity_choppiness_w": 1.0785624390748236,
    "equity_jerkiness": 0.03350427929986438,
    "equity_jerkiness_w": 0.0158980431922775,
    "expected_shortfall_1pct": 0.24495457704982865,
    "exponential_fit_error": 0.3582931674339633,
    "exponential_fit_error_w": 0.038845017581730465,
    "gain": 275.6303573457037,
    "gain_per_exposure_long": 55.14813072142931,
    "gain_per_exposure_short": 0.0,
    "loss_profit_ratio": 0.03780450005729555,
    "loss_profit_ratio_long": 0.03780450005729555,
    "loss_profit_ratio_short": 1.0,
    "loss_profit_ratio_w": 0.00628362946915407,
    "mdg": 0.003656157110229343,
    "mdg_per_exposure_long": 0.000731524031658532,
    "mdg_per_exposure_short": 0.0,
    "mdg_w": 0.0020100761575773452,
    "mdg_w_per_exposure_long": 0.0004021761019562515,
    "mdg_w_per_exposure_short": 0.0,
    "omega_ratio": 20.755125023796236,
    "omega_ratio_w": 119.69152396224017,
    "pnl_ratio_long_short": 1.0,
    "position_held_hours_max": 17.8,
    "position_held_hours_mean": 0.8115896188158962,
    "position_held_hours_median": 0.2,
    "position_unchanged_hours_max": 10.133333333333333,
    "positions_held_per_day": 7.555147058823529,
    "sharpe_ratio": 0.16959792174644028,
    "sharpe_ratio_w": 0.22628500143931873,
    "sortino_ratio": 0.35782775243975656,
    "sortino_ratio_w": 0.8799903865759735,
    "sterling_ratio": 0.07327302252333061,
    "sterling_ratio_w": 0.2573159883965108,
    "volume_pct_per_day_avg": 4.85798185103121,
    "volume_pct_per_day_avg_w": 2.3606692816824824
}