{
    "adg": 0.0028775557284275166,
    "adg_per_exposure_long": 0.0013377136016119737,
    "adg_per_exposure_short": 0.0,
    "adg_w": 0.0010764982964860837,
    "adg_w_per_exposure_long": 0.0005004408425856927,
    "adg_w_per_exposure_short": 0.0,
    "calmar_ratio": 0.019794614746920625,
    "calmar_ratio_w": 0.010311981948869293,
    "drawdown_worst": 0.14537063566115463,
    "drawdown_worst_mean_1pct": 0.08491622559900623,
    "equity_balance_diff_neg_max": 0.4125351999571009,
    "equity_balance_diff_neg_mean": 0.0015825504101051769,
    "equity_balance_diff_pos_max": 0.16893767641238172,
    "equity_balance_diff_pos_mean": 0.0007073324397999951,
    "equity_choppiness": 1.0743660635021133,
    "equity_choppiness_w": 1.435816478184176,
    "equity_jerkiness": 0.004373257300964581,
    "equity_jerkiness_w": 0.0024181625020298163,
    "expected_shortfall_1pct": 0.078377508889254,
    "exponential_fit_error": 0.25089689378121466,
    "exponential_fit_error_w": 0.025699006235295953,
    "gain": 119.95582316220164,
    "gain_per_exposure_long": 55.76487525554444,
    "gain_per_exposure_short": 0.0,
    "loss_profit_ratio": 0.01786572816948054,
    "loss_profit_ratio_long": 0.01786572816948054,
    "loss_profit_ratio_short": 1.0,
    "loss_profit_ratio_w": 0.0639985467809652,
    "mdg": 0.00021519331585977445,
    "mdg_per_exposure_long": 0.00010003873174644342,
    "mdg_per_exposure_short": 0.0,
    "mdg_w": 2.2353437241801536e-05,
    "mdg_w_per_exposure_long": 1.0391630905955808e-05,
    "mdg_w_per_exposure_short": 0.0,
    "omega_ratio": 71.81041303312047,
    "omega_ratio_w": 15.03673696400077,
    "pnl_ratio_long_short": 1.0,
    "position_held_hours_max": 46.88333333333333,
    "position_held_hours_mean": 0.6132570503929727,
    "position_held_hours_median": 0.15,
    "position_unchanged_hours_max": 35.416666666666664,
    "positions_held_per_day": 3.46218487394958,
    "sharpe_ratio": 0.10061971407110389,
    "sharpe_ratio_w": 0.06958299724383073,
    "sortino_ratio": 0.16757695808711712,
    "sortino_ratio_w": 0.07864342322904452,
    "sterling_ratio": 0.03388699519001222,
    "sterling_ratio_w": 0.014638945727441274,
    "volume_pct_per_day_avg": 0.9011169103090774,
    "volume_pct_per_day_avg_w": 0.6396841196190229
}