{
    "adg": 0.02347171607716514,
    "adg_per_exposure_long": 0.005960313884501051,
    "adg_per_exposure_short": 0.0,
    "adg_w": 0.0077267901125263935,
    "adg_w_per_exposure_long": 0.00196211023680203,
    "adg_w_per_exposure_short": 0.0,
    "calmar_ratio": 0.08286616225604992,
    "calmar_ratio_w": 0.030627663237082985,
    "drawdown_worst": 0.28324849900299937,
    "drawdown_worst_mean_1pct": 0.2661834540623366,
    "equity_balance_diff_neg_max": 0.5370464854853956,
    "equity_balance_diff_neg_mean": 0.00930204323659406,
    "equity_balance_diff_pos_max": 0.5199016779452689,
    "equity_balance_diff_pos_mean": 0.005156770029456631,
    "equity_choppiness": 1.2919221908730467,
    "equity_choppiness_w": 1.450087559035307,
    "equity_jerkiness": 0.03444346582734925,
    "equity_jerkiness_w": 0.01968566544952531,
    "expected_shortfall_1pct": 0.2661834540623367,
    "exponential_fit_error": 0.9667141320732234,
    "exponential_fit_error_w": 0.0980133220424583,
    "gain": 513.3367895854478,
    "gain_per_exposure_long": 130.35469517152052,
    "gain_per_exposure_short": 0.0,
    "loss_profit_ratio": 0.05919428639459979,
    "loss_profit_ratio_long": 0.05919428639459979,
    "loss_profit_ratio_short": 1.0,
    "loss_profit_ratio_w": 0.06934758712245744,
    "mdg": 0.0016468326755208593,
    "mdg_per_exposure_long": 0.0004181901156731486,
    "mdg_per_exposure_short": 0.0,
    "mdg_w": 0.0006087446878807683,
    "mdg_w_per_exposure_long": 0.00015458219600832104,
    "mdg_w_per_exposure_short": 0.0,
    "omega_ratio": 19.949797898924484,
    "omega_ratio_w": 43.85084206786781,
    "pnl_ratio_long_short": 1.0,
    "position_held_hours_max": 34.88333333333333,
    "position_held_hours_mean": 0.951123595505618,
    "position_held_hours_median": 0.35,
    "position_unchanged_hours_max": 23.366666666666667,
    "positions_held_per_day": 3.6394052044609664,
    "sharpe_ratio": 0.1534675011485998,
    "sharpe_ratio_w": 0.07992214705331781,
    "sortino_ratio": 0.31682572595778674,
    "sortino_ratio_w": 0.1001913619020586,
    "sterling_ratio": 0.08817871929661103,
    "sterling_ratio_w": 0.031158918941139098,
    "volume_pct_per_day_avg": 3.6705618973439247,
    "volume_pct_per_day_avg_w": 2.500386642779241
}